flask_headless_auth/__init__.py
flask_headless_auth/__version__.py
flask_headless_auth/config.py
flask_headless_auth/core.py
flask_headless_auth/default_models.py
flask_headless_auth/extensions.py
flask_headless_auth/interfaces.py
flask_headless_auth/data_access/__init__.py
flask_headless_auth/data_access/repository.py
flask_headless_auth/email_service/__init__.py
flask_headless_auth/email_service/brevo_service.py
flask_headless_auth/email_service/email_manager.py
flask_headless_auth/email_service/email_service.py
flask_headless_auth/email_service/gmail_service.py
flask_headless_auth/email_service/token.py
flask_headless_auth/managers/__init__.py
flask_headless_auth/managers/auth_manager.py
flask_headless_auth/managers/oauth_manager.py
flask_headless_auth/managers/rbac_manager.py
flask_headless_auth/managers/token_manager.py
flask_headless_auth/managers/user_manager.py
flask_headless_auth/mixins/__init__.py
flask_headless_auth/mixins/oauth.py
flask_headless_auth/mixins/role.py
flask_headless_auth/mixins/token.py
flask_headless_auth/mixins/user.py
flask_headless_auth/models/__init__.py
flask_headless_auth/models/oauth.py
flask_headless_auth/models/role.py
flask_headless_auth/models/token.py
flask_headless_auth/models/user.py
flask_headless_auth/oauth/__init__.py
flask_headless_auth/oauth/providers.py
flask_headless_auth/oauth/stateless_handler.py
flask_headless_auth/routes/__init__.py
flask_headless_auth/routes/auth.py
flask_headless_auth/utils/__init__.py
flask_headless_auth-0.1.4.dist-info/licenses/LICENSE
flask_headless_auth-0.1.4.dist-info/METADATA
flask_headless_auth-0.1.4.dist-info/WHEEL
flask_headless_auth-0.1.4.dist-info/top_level.txt
flask_headless_auth-0.1.4.dist-info/RECORD
