Metadata-Version: 2.4
Name: flask-headless-auth
Version: 0.1.4
Summary: Modern, headless authentication for Flask APIs. JWT + OAuth + RBAC in one line.
Author-email: Dhruv Agnihotri <dagni@umich.edu>
License-Expression: MIT
Project-URL: Homepage, https://github.com/Dhruvagnihotri/flask-headless-auth
Project-URL: Repository, https://github.com/Dhruvagnihotri/flask-headless-auth
Project-URL: Issues, https://github.com/Dhruvagnihotri/flask-headless-auth/issues
Project-URL: Documentation, https://github.com/Dhruvagnihotri/flask-headless-auth#readme
Keywords: flask,authentication,jwt,oauth,api,headless,react,rbac,mfa,nextjs,spa
Classifier: Development Status :: 3 - Alpha
Classifier: Intended Audience :: Developers
Classifier: Programming Language :: Python :: 3
Classifier: Programming Language :: Python :: 3.8
Classifier: Programming Language :: Python :: 3.9
Classifier: Programming Language :: Python :: 3.10
Classifier: Programming Language :: Python :: 3.11
Classifier: Programming Language :: Python :: 3.12
Classifier: Framework :: Flask
Classifier: Topic :: Software Development :: Libraries :: Python Modules
Classifier: Topic :: Internet :: WWW/HTTP :: Session
Requires-Python: >=3.8
License-File: LICENSE
Requires-Dist: Flask>=2.0.0
Requires-Dist: Flask-SQLAlchemy>=3.0.0
Requires-Dist: Flask-JWT-Extended>=4.5.0
Requires-Dist: Flask-Limiter>=3.3.0
Requires-Dist: Flask-Caching>=2.0.0
Requires-Dist: Flask-CORS>=4.0.0
Requires-Dist: Flask-WTF>=1.1.0
Requires-Dist: Flask-Talisman>=1.0.0
Requires-Dist: Authlib>=1.2.0
Requires-Dist: PyJWT>=2.8.0
Requires-Dist: python-dotenv>=1.0.0
Requires-Dist: PyYAML>=6.0
Requires-Dist: Werkzeug>=2.0.0
Requires-Dist: itsdangerous>=2.1.0
Provides-Extra: dev
Requires-Dist: pytest>=7.4.0; extra == "dev"
Requires-Dist: pytest-cov>=4.1.0; extra == "dev"
Requires-Dist: black>=23.7.0; extra == "dev"
Requires-Dist: flake8>=6.1.0; extra == "dev"
Provides-Extra: email
Requires-Dist: brevo-python>=1.0.0; extra == "email"
Dynamic: license-file
